Asialuxe/__init__.py
asialuxe-0.10.dist-info/METADATA
asialuxe-0.10.dist-info/WHEEL
asialuxe-0.10.dist-info/top_level.txt
asialuxe-0.10.dist-info/RECORD
