Metadata-Version: 2.4
Name: Asialuxe
Version: 0.10
Summary: Asialuxe API
Author: rodnoc
Author-email: rodnoc@list.ru
Classifier: Programming Language :: Python :: 3
Classifier: License :: OSI Approved :: MIT License
Classifier: Operating System :: OS Independent
Requires-Python: >=3.11
Requires-Dist: requests
Dynamic: author
Dynamic: author-email
Dynamic: classifier
Dynamic: requires-dist
Dynamic: requires-python
Dynamic: summary
